glypy/version.py
glypy/__init__.py
glypy/plot/fragment_annotation.py
glypy/plot/iupac_symbols.py
glypy/plot/draw_tree.py
glypy/plot/__init__.py
glypy/plot/common.py
glypy/plot/cfg_symbols.py
glypy/plot/snfg_symbols.py
glypy/plot/geometry.py
glypy/plot/symbolic_nomenclature.py
glypy/plot/topological_layout.py
glypy/plot/buchheim.py
glypy/io/monosaccharidedb.py
glypy/io/cfg.py
glypy/io/_glycordf.py
glypy/io/gws.py
glypy/io/linear_code.py
glypy/io/__init__.py
glypy/io/format_constants_map.py
glypy/io/gnome.py
glypy/io/delimited.py
glypy/io/glyconnect.py
glypy/io/tree_builder_utils.py
glypy/io/file_utils.py
glypy/io/glycomedb.py
glypy/io/iupac.py
glypy/io/glyspace.py
glypy/io/byonic.py
glypy/io/glycoct.py
glypy/io/glycoct_xml.py
glypy/io/wurcs/carbon_descriptors.py
glypy/io/wurcs/basetype_conversion.py
glypy/io/wurcs/substituent_conversion.py
glypy/io/wurcs/__init__.py
glypy/io/wurcs/parser.py
glypy/io/wurcs/utils.py
glypy/io/wurcs/writer.py
glypy/io/wurcs/node_type.py
glypy/io/nomenclature/synonyms.py
glypy/io/nomenclature/__init__.py
glypy/io/nomenclature/identity.py
glypy/io/nomenclature/data/__init__.py
glypy/io/nomenclature/data/monosaccharide_schematic.json
glypy/io/nomenclature/data/monosaccharide_synonyms.json
glypy/io/nomenclature/data/find_synonyms.py
glypy/io/data/make_enzyme_json.py
glypy/io/data/glycan.owl
glypy/io/data/fetch_definitions.py
glypy/io/data/__init__.py
glypy/io/data/enzyme.json
glypy/algorithms/similarity.py
glypy/algorithms/database.py
glypy/algorithms/__init__.py
glypy/algorithms/canonicalize.py
glypy/algorithms/storage.py
glypy/algorithms/subtree_search/common_subgraph.py
glypy/algorithms/subtree_search/__init__.py
glypy/algorithms/subtree_search/inclusion.py
glypy/utils/cenum.pxd
glypy/utils/cenum.c
glypy/utils/compat.py
glypy/utils/__init__.py
glypy/utils/multimap.py
glypy/utils/cenum.cpython-311-darwin.so
glypy/utils/enum.py
glypy/utils/lazy.py
glypy/utils/base.py
glypy-1.0.17.dist-info/RECORD
glypy-1.0.17.dist-info/WHEEL
glypy-1.0.17.dist-info/top_level.txt
glypy-1.0.17.dist-info/METADATA
glypy-1.0.17.dist-info/licenses/LICENSE
glypy-1.0.17.dist-info/licenses/NOTICE
