Metadata-Version: 2.4
Name: glypy
Version: 1.0.17
Summary: A Glycoinformatics Toolkit
Home-page: https://github.com/mobiusklein/glypy
Maintainer: Joshua Klein
Maintainer-email: jaklein@bu.edu
Project-URL: Documentation, https://glypy.readthedocs.io/
Project-URL: Repository, https://github.com/mobiusklein/glypy
Keywords: glycomics glycan carbohydrate glycoinformatics glypy n-linked o-linked glycosaminoglycan
Classifier: Development Status :: 5 - Production/Stable
Classifier: Intended Audience :: Science/Research
Classifier: License :: OSI Approved :: Apache Software License
Classifier: Topic :: Scientific/Engineering :: Bio-Informatics
Classifier: Programming Language :: Python :: 2.7
Classifier: Programming Language :: Python :: 3
License-File: LICENSE
License-File: NOTICE
Requires-Dist: hjson
Requires-Dist: six
Provides-Extra: plot
Requires-Dist: matplotlib>=2.2.0; extra == "plot"
Provides-Extra: glyspace
Requires-Dist: requests; extra == "glyspace"
Requires-Dist: rdflib; extra == "glyspace"
Requires-Dist: SPARQLWrapper; extra == "glyspace"
Provides-Extra: all
Requires-Dist: requests; extra == "all"
Requires-Dist: matplotlib>=2.2.0; extra == "all"
Requires-Dist: SPARQLWrapper; extra == "all"
Requires-Dist: rdflib; extra == "all"
Dynamic: classifier
Dynamic: description
Dynamic: home-page
Dynamic: keywords
Dynamic: license-file
Dynamic: maintainer
Dynamic: maintainer-email
Dynamic: project-url
Dynamic: provides-extra
Dynamic: requires-dist
Dynamic: summary
